MORPHO/__init__.py
MORPHO/combineCSV.py
MORPHO/createConfig.py
MORPHO/loadingBar.py
MORPHO/modeSelect.py
MORPHO/playBeep.py
MORPHO/uniqueID.py
morpho_toolkit-0.2.2.dev0.dist-info/licenses/LICENSE
morpho_toolkit-0.2.2.dev0.dist-info/METADATA
morpho_toolkit-0.2.2.dev0.dist-info/WHEEL
morpho_toolkit-0.2.2.dev0.dist-info/top_level.txt
morpho_toolkit-0.2.2.dev0.dist-info/RECORD
