Metadata-Version: 2.4
Name: morpho-toolkit
Version: 0.2.2.dev0
Summary: The MORPHO data-science toolkit.
Author-email: EstesJorie <joe.tresise@aol.com>
License: MIT
Project-URL: Source, https://github.com/EstesJorie/Morpho
Project-URL: Tracker, https://github.com/EstesJorie/Morpho/issues
Keywords: data analysis,data science
Classifier: Programming Language :: Python :: 3
Classifier: Programming Language :: Python :: 3.8
Classifier: License :: OSI Approved :: MIT License
Classifier: Operating System :: OS Independent
Requires-Python: >=3.8
License-File: LICENSE
Requires-Dist: pandas
Requires-Dist: glob2
Requires-Dist: tqdm==4.66.3
Requires-Dist: numpy
Requires-Dist: matplotlib
Requires-Dist: seaborn
Requires-Dist: scikit-learn
Requires-Dist: scipy
Requires-Dist: statsmodels
Requires-Dist: icecream
Requires-Dist: colorama
Requires-Dist: pytest
Requires-Dist: build
Provides-Extra: dev
Requires-Dist: plotly; extra == "dev"
Requires-Dist: xlrd; extra == "dev"
Dynamic: license-file
